iv_sherlock/__init__.py
iv_sherlock/__main__.py
iv_sherlock/config_manager.py
iv_sherlock/cve_evaluator.py
iv_sherlock/image_vul_parser.py
iv_sherlock/report_generator.py
iv_sherlock/conf/config.toml
iv_sherlock/conf/constant.py
iv_sherlock/templates/end_template.html
iv_sherlock/templates/gen_report.html
iv_sherlock/templates/vul_report.html
iv_sherlock/templates/vul_simple.html
iv_sherlock-0.3.0.dist-info/LICENSE
iv_sherlock-0.3.0.dist-info/METADATA
iv_sherlock-0.3.0.dist-info/WHEEL
iv_sherlock-0.3.0.dist-info/entry_points.txt
iv_sherlock-0.3.0.dist-info/top_level.txt
iv_sherlock-0.3.0.dist-info/RECORD
