Metadata-Version: 2.2
Name: iv_sherlock
Version: 0.3.0
Summary: This packge parses the vulnerability report(.json) generated by trivy for container images, then generate human readable report(.html or .pdf) 
Author-email: Pengfei <pengfei.liu@casd.eu>
License: MIT License
Project-URL: repository, https://github.com/CASD-EU/ImageVulnAnalyzer
Project-URL: documentation, https://github.com/CASD-EU/ImageVulnAnalyzer
Keywords: docker image vulnerability,trivy
Classifier: License :: OSI Approved :: MIT License
Classifier: Programming Language :: Python
Classifier: Programming Language :: Python :: 3
Requires-Python: >=3.11
License-File: LICENSE
Requires-Dist: pandas
Requires-Dist: jinja2
Provides-Extra: build
Requires-Dist: build; extra == "build"
Requires-Dist: twine; extra == "build"
Provides-Extra: dev
Requires-Dist: black; extra == "dev"
Requires-Dist: bumpver; extra == "dev"
Requires-Dist: isort; extra == "dev"
Requires-Dist: mypy; extra == "dev"
Requires-Dist: pytest; extra == "dev"
Requires-Dist: pandas-stubs; extra == "dev"
